trollo/__init__.py
trollo/actions.py
trollo/boards.py
trollo/cards.py
trollo/checklists.py
trollo/labels.py
trollo/lists.py
trollo/members.py
trollo/notifications.py
trollo/organizations.py
trollo/search.py
trollo/tokens.py
trollo/types.py
trollo-0.2.5.data/data/LICENSE.txt
trollo-0.2.5.dist-info/LICENSE.txt
trollo-0.2.5.dist-info/METADATA
trollo-0.2.5.dist-info/WHEEL
trollo-0.2.5.dist-info/top_level.txt
trollo-0.2.5.dist-info/RECORD
