Metadata-Version: 2.1
Name: trollo
Version: 0.2.5
Summary: UNKNOWN
Home-page: http://github.com/lhh/trollo
Author: Red Hat
Author-email: lhh@redhat.com
Maintainer: Lon Hohberger
Maintainer-email: lon@metamorphism.com
License: BSD
Platform: UNKNOWN
Classifier: Development Status :: 4 - Beta
Classifier: Intended Audience :: Developers
Classifier: Natural Language :: English
Classifier: Operating System :: MacOS :: MacOS X
Classifier: Operating System :: Microsoft :: Windows
Classifier: Operating System :: POSIX
Classifier: Operating System :: POSIX :: BSD
Classifier: Operating System :: POSIX :: Linux
Classifier: Programming Language :: Python
Classifier: Topic :: Internet :: WWW/HTTP
Classifier: Topic :: Software Development
Classifier: Topic :: Software Development :: Libraries
Classifier: Topic :: Software Development :: Libraries :: Python Modules
Classifier: Topic :: Utilities
License-File: LICENSE.txt
Requires-Dist: requests (>=2.1.0)
Requires-Dist: requests-toolbelt
